odoo/addons/importar_lineas_compra/.gitignore
odoo/addons/importar_lineas_compra/CHANGELOG.md
odoo/addons/importar_lineas_compra/LICENSE
odoo/addons/importar_lineas_compra/Readme.md
odoo/addons/importar_lineas_compra/__init__.py
odoo/addons/importar_lineas_compra/__manifest__.py
odoo/addons/importar_lineas_compra/importar_lineas_compra.py
odoo/addons/importar_lineas_compra/importar_lineas_compra_view.xml
odoo/addons/importar_lineas_compra/Sample Files/purchase_order_line.csv
odoo/addons/importar_lineas_compra/Sample Files/purchase_order_line.xls
odoo/addons/importar_lineas_compra/data/attachment_sample.xml
odoo/addons/importar_lineas_compra/i18n/es.po
odoo/addons/importar_lineas_compra/security/ir.model.access.csv
odoo/addons/importar_lineas_compra/wizards/confirm_wizard_view.xml
odoo_addon_importar_lineas_compra-17.0.1.0.3.dist-info/METADATA
odoo_addon_importar_lineas_compra-17.0.1.0.3.dist-info/WHEEL
odoo_addon_importar_lineas_compra-17.0.1.0.3.dist-info/top_level.txt
odoo_addon_importar_lineas_compra-17.0.1.0.3.dist-info/RECORD
