Metadata-Version: 2.1
Name: odoo-addon-importar_lineas_compra
Version: 17.0.1.0.3
Requires-Python: >=3.10
Requires-Dist: odoo>=17.0a,<17.1dev
Requires-Dist: openpyxl~=3.1.5
Summary: =?utf-8?q?Importar_de_varias_maneras_l=C3=ADneas_de_compra_en_un_pedido=2E?=
Home-page: https://framagit.org/devcontrol
License: AGPL-3
Author: Colectivo DEVCONTROL
Classifier: Programming Language :: Python
Classifier: Framework :: Odoo
Classifier: Framework :: Odoo :: 17.0
Classifier: License :: OSI Approved :: GNU Affero General Public License v3
